Metadata-Version: 2.1
Name: KingDataGenerator
Version: 1.3
Summary: This packet generates fictitious human data, uniquely (names,emails,password,personal-documents), for the use of the develpoer
Author: Black King
Keywords: data human,dados pessoais,fordev,4dev,generator,gerador
License-File: license.txt
